[
    {
        "question": "1. What is the fundamental idea behind DSDM?",
        "options": [
            "C. Adjusting the amount of work",
            "D. None of the above",
            "A. Fixing the amount of functionality",
            "B. Fixing time and resources"
        ],
        "correct_answer": "C. Adjusting the amount of work"
    },
    {
        "question": "2. What is a key focus of DSDM teams?",
        "options": [
            "D. None of the above",
            "A. Achieving personal objectives",
            "B. Aligning with greater business objectives",
            "C. Working independently"
        ],
        "correct_answer": "D. None of the above"
    },
    {
        "question": "3. Why is prompt delivery important in DSDM projects?",
        "options": [
            "A. To delay projects",
            "C. To increase costs",
            "D. None of the above",
            "B. To reap benefits early"
        ],
        "correct_answer": "A. To delay projects"
    },
    {
        "question": "4. Which of the following tools is NOT used to provide updates in DSDM?",
        "options": [
            "D. Electronic",
            "B. Verbal",
            "A. Written",
            "C. Visual"
        ],
        "correct_answer": "D. Electronic"
    },
    {
        "question": "5. What role is vital in providing structure for DSDM teams?",
        "options": [
            "A. Tester",
            "C. Customer",
            "D. Developer",
            "B. Project manager"
        ],
        "correct_answer": "A. Tester"
    },
    {
        "question": "6. What is reviewed during the stage of determining project realism?",
        "options": [
            "D. All of the above",
            "B. Timeline",
            "A. Budget",
            "C. Specifications"
        ],
        "correct_answer": "D. All of the above"
    },
    {
        "question": "7. What happens during the prototype building phase in DSDM?",
        "options": [
            "D. None of the above",
            "C. Building multiple prototypes",
            "A. Testing and evaluation",
            "B. Learning to operate the product"
        ],
        "correct_answer": "D. None of the above"
    },
    {
        "question": "8. Which role in DSDM is responsible for giving teams ad hoc business advice?",
        "options": [
            "D. None of the above",
            "C. DSDM Coach",
            "A. Business Advisor",
            "B. Solution Tester"
        ],
        "correct_answer": "D. None of the above"
    },
    {
        "question": "9. What is one of the principles of Kanban?",
        "options": [
            "A. Start with what do want now",
            "C. Use unlimited work-in-process",
            "D. None of the above",
            "B. Make process policies explicit"
        ],
        "correct_answer": "A. Start with what do want now"
    },
    {
        "question": "10. How do teams measure their effectiveness in Kanban?",
        "options": [
            "D. All of the above",
            "C. Collective understanding of issues",
            "B. Shared vision of a better future",
            "A. Shared understanding of theories"
        ],
        "correct_answer": "D. All of the above"
    }
]